smiles_encoder/__init__.py
smiles_encoder/encoder.py
smiles_encoder/version.py
smiles_encoder-0.1.1.dist-info/LICENSE
smiles_encoder-0.1.1.dist-info/METADATA
smiles_encoder-0.1.1.dist-info/WHEEL
smiles_encoder-0.1.1.dist-info/top_level.txt
smiles_encoder-0.1.1.dist-info/RECORD
