Metadata-Version: 2.1
Name: smiles_encoder
Version: 0.1.1
Summary: One-hot encoding for simple molecular-input line-entry system (SMILES) strings
Author-email: Travis Kessler <travis.j.kessler@gmail.com>
Project-URL: Homepage, https://github.com/tjkessler/smiles-encoder
Project-URL: Bug Tracker, https://github.com/tjkessler/smiles-encoder/issues
Classifier: Programming Language :: Python :: 3.11
Classifier: License :: OSI Approved :: MIT License
Classifier: Operating System :: OS Independent
Requires-Python: >=3.11
License-File: LICENSE
